{
	"mannschaft0" :
		{
			"name" : "[Mannschaftsname 1]",
			"volle" : "[Volle Mannschaft 1]",
			"abr" : "[Abraeumer Mannschaft 1]",
			"f" : "[Fehlwuerfe Mannschaft 1]",
			"gesamt": "[Holz Mannschaft 1]",
			"mp": "[Mannschaftspunkte Mannschaft 1]",
			"spieler0" :
				{
					"spielername" : "[SpielernameAw 1, 1]",
					"wurf" : "[Wurf Spieler 1, 1]",
					"gesamt" : "[Holz Spieler 1, 1]",
					"sp" : "[Satzpunkte Spieler 1, 1]",
					"satz" : "[Holz Satz 1, 1, 1];[Holz Satz 2, 1, 1];[Holz Satz 3, 1, 1];[Holz Satz 4, 1, 1]"
				},
			"spieler1" :
				{
					"spielername" : "[SpielernameAw 1, 2]",
					"wurf" : "[Wurf Spieler 1, 2]",
					"gesamt" : "[Holz Spieler 1, 2]",
					"sp" : "[Satzpunkte Spieler 1, 2]",
					"satz" : "[Holz Satz 1, 1, 2];[Holz Satz 2, 1, 2];[Holz Satz 3, 1, 2];[Holz Satz 4, 1, 2]"
				},
			"spieler2" :
				{
					"spielername" : "[SpielernameAw 1, 3]",
					"wurf" : "[Wurf Spieler 1, 3]",
					"gesamt" : "[Holz Spieler 1, 3]",
					"sp" : "[Satzpunkte Spieler 1, 3]",
					"satz" : "[Holz Satz 1, 1, 3];[Holz Satz 2, 1, 3];[Holz Satz 3, 1, 3];[Holz Satz 4, 1, 3]"
				},
			"spieler3" :
				{
					"spielername" : "[SpielernameAw 1, 4]",
					"wurf" : "[Wurf Spieler 1, 4]",
					"gesamt" : "[Holz Spieler 1, 4]",
					"sp" : "[Satzpunkte Spieler 1, 4]",
					"satz" : "[Holz Satz 1, 1, 4];[Holz Satz 2, 1, 4];[Holz Satz 3, 1, 4];[Holz Satz 4, 1, 4]"
				},
			"spieler4" :
				{
					"spielername" : "[SpielernameAw 1, 5]",
					"wurf" : "[Wurf Spieler 1, 5]",
					"gesamt" : "[Holz Spieler 1, 5]",
					"sp" : "[Satzpunkte Spieler 1, 5]",
					"satz" : "[Holz Satz 1, 1, 5];[Holz Satz 2, 1, 5];[Holz Satz 3, 1, 5];[Holz Satz 4, 1, 5]"
				},
			"spieler5" :
				{
					"spielername" : "[SpielernameAw 1, 6]",
					"wurf" : "[Wurf Spieler 1, 6]",
					"gesamt" : "[Holz Spieler 1, 6]",
					"sp" : "[Satzpunkte Spieler 1, 6]",
					"satz" : "[Holz Satz 1, 1, 6];[Holz Satz 2, 1, 6];[Holz Satz 3, 1, 6];[Holz Satz 4, 1, 6]"
				}
		},
	"mannschaft1" :
		{
			"name" : "[Mannschaftsname 2]",
			"volle" : "[Volle Mannschaft 2]",
			"abr" : "[Abraeumer Mannschaft 2]",
			"f" : "[Fehlwuerfe Mannschaft 2]",
			"gesamt": "[Holz Mannschaft 2]",
			"mp": "[Mannschaftspunkte Mannschaft 2]",
			"spieler0" :
				{
					"spielername" : "[SpielernameAw 2, 1]",
					"wurf" : "[Wurf Spieler 2, 1]",
					"gesamt" : "[Holz Spieler 2, 1]",
					"sp" : "[Satzpunkte Spieler 2, 1]",
					"satz" : "[Holz Satz 1, 2, 1];[Holz Satz 2, 2, 1];[Holz Satz 3, 2, 1];[Holz Satz 4, 2, 1]"
				},
			"spieler1" :
				{
					"spielername" : "[SpielernameAw 2, 2]",
					"wurf" : "[Wurf Spieler 2, 2]",
					"gesamt" : "[Holz Spieler 2, 2]",
					"sp" : "[Satzpunkte Spieler 2, 2]",
					"satz" : "[Holz Satz 1, 2, 2];[Holz Satz 2, 2, 2];[Holz Satz 3, 2, 2];[Holz Satz 4, 2, 2]"
				},
			"spieler2" :
				{
					"spielername" : "[SpielernameAw 2, 3]",
					"wurf" : "[Wurf Spieler 2, 3]",
					"gesamt" : "[Holz Spieler 2, 3]",
					"sp" : "[Satzpunkte Spieler 2, 3]",
					"satz" : "[Holz Satz 1, 2, 3];[Holz Satz 2, 2, 3];[Holz Satz 3, 2, 3];[Holz Satz 4, 2, 3]"
				},
			"spieler3" :
				{
					"spielername" : "[SpielernameAw 2, 4]",
					"wurf" : "[Wurf Spieler 2, 4]",
					"gesamt" : "[Holz Spieler 2, 4]",
					"sp" : "[Satzpunkte Spieler 2, 4]",
					"satz" : "[Holz Satz 1, 2, 4];[Holz Satz 2, 2, 4];[Holz Satz 3, 2, 4];[Holz Satz 4, 2, 4]"
				},
			"spieler4" :
				{
					"spielername" : "[SpielernameAw 2, 5]",
					"wurf" : "[Wurf Spieler 2, 5]",
					"gesamt" : "[Holz Spieler 2, 5]",
					"sp" : "[Satzpunkte Spieler 2, 5]",
					"satz" : "[Holz Satz 1, 2, 5];[Holz Satz 2, 2, 5];[Holz Satz 3, 2, 5];[Holz Satz 4, 2, 5]"
				},
			"spieler5" :
				{
					"spielername" : "[SpielernameAw 2, 6]",
					"wurf" : "[Wurf Spieler 2, 6]",
					"gesamt" : "[Holz Spieler 2, 6]",
					"sp" : "[Satzpunkte Spieler 2, 6]",
					"satz" : "[Holz Satz 1, 2, 6];[Holz Satz 2, 2, 6];[Holz Satz 3, 2, 6];[Holz Satz 4, 2, 6]"
				}
		}
}
